<?xml version="1.0" encoding="utf-8"?>
<ArrayOfProduct>
  <Product>
    <barcode>100</barcode>
    <productName>Milk</productName>
    <price>4.5</price>
    <quantityInStock>49</quantityInStock>
    <category>Milky</category>
  </Product>
  <Product>
    <barcode>200</barcode>
    <productName>Chocolate</productName>
    <price>3</price>
    <quantityInStock>30</quantityInStock>
    <category>Milky</category>
  </Product>
  <Product>
    <barcode>300</barcode>
    <productName>Cheese</productName>
    <price>2.5</price>
    <quantityInStock>20</quantityInStock>
    <category>Milky</category>
  </Product>
  <Product>
    <barcode>400</barcode>
    <productName>Tomato</productName>
    <price>4</price>
    <quantityInStock>30</quantityInStock>
    <category>FruitVegetables</category>
  </Product>
  <Product>
    <barcode>500</barcode>
    <productName>Cucumber</productName>
    <price>5</price>
    <quantityInStock>30</quantityInStock>
    <category>FruitVegetables</category>
  </Product>
  <Product>
    <barcode>600</barcode>
    <productName>Carrot</productName>
    <price>3</price>
    <quantityInStock>30</quantityInStock>
    <category>FruitVegetables</category>
  </Product>
  <Product>
    <barcode>700</barcode>
    <productName>Candy</productName>
    <price>1</price>
    <quantityInStock>100</quantityInStock>
    <category>Sweets</category>
  </Product>
  <Product>
    <barcode>800</barcode>
    <productName>Bamba</productName>
    <price>4</price>
    <quantityInStock>60</quantityInStock>
    <category>Sweets</category>
  </Product>
  <Product>
    <barcode>900</barcode>
    <productName>Bisli</productName>
    <price>5.5</price>
    <quantityInStock>70</quantityInStock>
    <category>Sweets</category>
  </Product>
  <Product>
    <barcode>1000</barcode>
    <productName>Chips</productName>
    <price>3.5</price>
    <quantityInStock>70</quantityInStock>
    <category>Sweets</category>
  </Product>
  <Product>
    <barcode>1100</barcode>
    <productName>Bread</productName>
    <price>5</price>
    <quantityInStock>30</quantityInStock>
    <category>Breads</category>
  </Product>
  <Product>
    <barcode>1200</barcode>
    <productName>Roll</productName>
    <price>11</price>
    <quantityInStock>25</quantityInStock>
    <category>Breads</category>
  </Product>
  <Product>
    <barcode>1300</barcode>
    <productName>Pita</productName>
    <price>14</price>
    <quantityInStock>20</quantityInStock>
    <category>Breads</category>
  </Product>
  <Product>
    <barcode>1400</barcode>
    <productName>Wipes</productName>
    <price>18</price>
    <quantityInStock>10</quantityInStock>
    <category>Cleanliness</category>
  </Product>
  <Product>
    <barcode>1500</barcode>
    <productName>Econmica</productName>
    <price>25</price>
    <quantityInStock>15</quantityInStock>
    <category>Cleanliness</category>
  </Product>
</ArrayOfProduct>